{"E09000003":{"index-entry-number":"30","entry-number":"30","entry-timestamp":"2017-11-28T14:41:29Z","key":"E09000003","item":[{"statistical-geography-london-borough-eng":"E09000003","local-authority-eng":"BNE","start-date":"2009-01-01"}]},"E09000025":{"index-entry-number":"10","entry-number":"10","entry-timestamp":"2017-11-28T14:41:29Z","key":"E09000025","item":[{"statistical-geography-london-borough-eng":"E09000025","local-authority-eng":"NWM","start-date":"2009-01-01"}]},"E09000002":{"index-entry-number":"33","entry-number":"33","entry-timestamp":"2017-11-28T14:41:29Z","key":"E09000002","item":[{"statistical-geography-london-borough-eng":"E09000002","local-authority-eng":"BDG","start-date":"2009-01-01"}]},"E09000024":{"index-entry-number":"11","entry-number":"11","entry-timestamp":"2017-11-28T14:41:29Z","key":"E09000024","item":[{"statistical-geography-london-borough-eng":"E09000024","local-authority-eng":"MRT","start-date":"2009-01-01"}]},"E09000005":{"index-entry-number":"32","entry-number":"32","entry-timestamp":"2017-11-28T14:41:29Z","key":"E09000005","item":[{"statistical-geography-london-borough-eng":"E09000005","local-authority-eng":"BEN","start-date":"2009-01-01"}]},"E09000027":{"index-entry-number":"8","entry-number":"8","entry-timestamp":"2017-11-28T14:41:29Z","key":"E09000027","item":[{"statistical-geography-london-borough-eng":"E09000027","local-authority-eng":"RIC","start-date":"2009-01-01"}]},"E09000004":{"index-entry-number":"31","entry-number":"31","entry-timestamp":"2017-11-28T14:41:29Z","key":"E09000004","item":[{"statistical-geography-london-borough-eng":"E09000004","local-authority-eng":"BEX","start-date":"2009-01-01"}]},"E09000026":{"index-entry-number":"9","entry-number":"9","entry-timestamp":"2017-11-28T14:41:29Z","key":"E09000026","item":[{"statistical-geography-london-borough-eng":"E09000026","local-authority-eng":"RDB","start-date":"2009-01-01"}]},"E09000007":{"index-entry-number":"28","entry-number":"28","entry-timestamp":"2017-11-28T14:41:29Z","key":"E09000007","item":[{"statistical-geography-london-borough-eng":"E09000007","local-authority-eng":"CMD","start-date":"2009-01-01"}]},"E09000029":{"index-entry-number":"7","entry-number":"7","entry-timestamp":"2017-11-28T14:41:29Z","key":"E09000029","item":[{"statistical-geography-london-borough-eng":"E09000029","local-authority-eng":"STN","start-date":"2009-01-01"}]},"E09000006":{"index-entry-number":"29","entry-number":"29","entry-timestamp":"2017-11-28T14:41:29Z","key":"E09000006","item":[{"statistical-geography-london-borough-eng":"E09000006","local-authority-eng":"BRY","start-date":"2009-01-01"}]},"E09000028":{"index-entry-number":"6","entry-number":"6","entry-timestamp":"2017-11-28T14:41:29Z","key":"E09000028","item":[{"statistical-geography-london-borough-eng":"E09000028","local-authority-eng":"SWK","start-date":"2009-01-01"}]},"E09000009":{"index-entry-number":"26","entry-number":"26","entry-timestamp":"2017-11-28T14:41:29Z","key":"E09000009","item":[{"statistical-geography-london-borough-eng":"E09000009","local-authority-eng":"EAL","start-date":"2009-01-01"}]},"E09000008":{"index-entry-number":"27","entry-number":"27","entry-timestamp":"2017-11-28T14:41:29Z","key":"E09000008","item":[{"statistical-geography-london-borough-eng":"E09000008","local-authority-eng":"CRY","start-date":"2009-01-01"}]},"E09000021":{"index-entry-number":"14","entry-number":"14","entry-timestamp":"2017-11-28T14:41:29Z","key":"E09000021","item":[{"statistical-geography-london-borough-eng":"E09000021","local-authority-eng":"KTT","start-date":"2009-01-01"}]},"E09000020":{"index-entry-number":"15","entry-number":"15","entry-timestamp":"2017-11-28T14:41:29Z","key":"E09000020","item":[{"statistical-geography-london-borough-eng":"E09000020","local-authority-eng":"KEC","start-date":"2009-01-01"}]},"E09000023":{"index-entry-number":"12","entry-number":"12","entry-timestamp":"2017-11-28T14:41:29Z","key":"E09000023","item":[{"statistical-geography-london-borough-eng":"E09000023","local-authority-eng":"LEW","start-date":"2009-01-01"}]},"E09000001":{"index-entry-number":"1","entry-number":"1","entry-timestamp":"2017-11-28T14:41:29Z","key":"E09000001","item":[{"statistical-geography-london-borough-eng":"E09000001","local-authority-eng":"LND","start-date":"2009-01-01"}]},"E09000022":{"index-entry-number":"13","entry-number":"13","entry-timestamp":"2017-11-28T14:41:29Z","key":"E09000022","item":[{"statistical-geography-london-borough-eng":"E09000022","local-authority-eng":"LBH","start-date":"2009-01-01"}]},"E09000014":{"index-entry-number":"17","entry-number":"17","entry-timestamp":"2017-11-28T14:41:29Z","key":"E09000014","item":[{"statistical-geography-london-borough-eng":"E09000014","local-authority-eng":"HRY","start-date":"2009-01-01"}]},"E09000013":{"index-entry-number":"20","entry-number":"20","entry-timestamp":"2017-11-28T14:41:29Z","key":"E09000013","item":[{"statistical-geography-london-borough-eng":"E09000013","local-authority-eng":"HMF","start-date":"2009-01-01"}]},"E09000016":{"index-entry-number":"23","entry-number":"23","entry-timestamp":"2017-11-28T14:41:29Z","key":"E09000016","item":[{"statistical-geography-london-borough-eng":"E09000016","local-authority-eng":"HAV","start-date":"2009-01-01"}]},"E09000015":{"index-entry-number":"18","entry-number":"18","entry-timestamp":"2017-11-28T14:41:29Z","key":"E09000015","item":[{"statistical-geography-london-borough-eng":"E09000015","local-authority-eng":"HRW","start-date":"2009-01-01"}]},"E09000018":{"index-entry-number":"19","entry-number":"19","entry-timestamp":"2017-11-28T14:41:29Z","key":"E09000018","item":[{"statistical-geography-london-borough-eng":"E09000018","local-authority-eng":"HNS","start-date":"2009-01-01"}]},"E09000017":{"index-entry-number":"21","entry-number":"21","entry-timestamp":"2017-11-28T14:41:29Z","key":"E09000017","item":[{"statistical-geography-london-borough-eng":"E09000017","local-authority-eng":"HIL","start-date":"2009-01-01"}]},"E09000019":{"index-entry-number":"16","entry-number":"16","entry-timestamp":"2017-11-28T14:41:29Z","key":"E09000019","item":[{"statistical-geography-london-borough-eng":"E09000019","local-authority-eng":"ISL","start-date":"2009-01-01"}]},"E09000030":{"index-entry-number":"5","entry-number":"5","entry-timestamp":"2017-11-28T14:41:29Z","key":"E09000030","item":[{"statistical-geography-london-borough-eng":"E09000030","local-authority-eng":"TWH","start-date":"2009-01-01"}]},"E09000010":{"index-entry-number":"25","entry-number":"25","entry-timestamp":"2017-11-28T14:41:29Z","key":"E09000010","item":[{"statistical-geography-london-borough-eng":"E09000010","local-authority-eng":"ENF","start-date":"2009-01-01"}]},"E09000032":{"index-entry-number":"3","entry-number":"3","entry-timestamp":"2017-11-28T14:41:29Z","key":"E09000032","item":[{"statistical-geography-london-borough-eng":"E09000032","local-authority-eng":"WND","start-date":"2009-01-01"}]},"E09000031":{"index-entry-number":"4","entry-number":"4","entry-timestamp":"2017-11-28T14:41:29Z","key":"E09000031","item":[{"statistical-geography-london-borough-eng":"E09000031","local-authority-eng":"WFT","start-date":"2009-01-01"}]},"E09000012":{"index-entry-number":"22","entry-number":"22","entry-timestamp":"2017-11-28T14:41:29Z","key":"E09000012","item":[{"statistical-geography-london-borough-eng":"E09000012","local-authority-eng":"HCK","start-date":"2009-01-01"}]},"E09000011":{"index-entry-number":"24","entry-number":"24","entry-timestamp":"2017-11-28T14:41:29Z","key":"E09000011","item":[{"statistical-geography-london-borough-eng":"E09000011","local-authority-eng":"GRE","start-date":"2009-01-01"}]},"E09000033":{"index-entry-number":"2","entry-number":"2","entry-timestamp":"2017-11-28T14:41:29Z","key":"E09000033","item":[{"statistical-geography-london-borough-eng":"E09000033","local-authority-eng":"WSM","start-date":"2009-01-01"}]}}